Metadata-Version: 2.1
Name: django-galleryfield
Version: 2.2.0
Summary: Django AJAX upload widget and model field for multiple images, featuring drag & drop uploading, upload progress bar, sortable and croppable image gallery
Home-page: https://github.com/dzhuang/django-galleryfield
Author: Dong Zhuang
Author-email: dzhuang.scut@gmail.com
License: MIT
Keywords: django ajax html5 upload widget images gallery sorting crop progressthumbnails multiple GalleryField admin forms field
Classifier: Development Status :: 5 - Production/Stable
Classifier: Environment :: Web Environment
Classifier: Framework :: Django
Classifier: Framework :: Django :: 3.1
Classifier: Framework :: Django :: 3.2
Classifier: Framework :: Django :: 4
Classifier: Intended Audience :: Developers
Classifier: License :: OSI Approved :: MIT License
Classifier: Operating System :: OS Independent
Classifier: Programming Language :: Python :: 3
Classifier: Programming Language :: Python :: 3 :: Only
Classifier: Programming Language :: Python :: 3.6
Classifier: Programming Language :: Python :: 3.7
Classifier: Programming Language :: Python :: 3.8
Classifier: Programming Language :: Python :: 3.9
Classifier: Topic :: Internet :: WWW/HTTP
Classifier: Topic :: Software Development :: Libraries :: Python Modules
License-File: LICENSE.txt
Requires-Dist: sorl-thumbnail
Requires-Dist: pillow
